{
    "question": "1000+100\u00f7900-1000\u00f7200 \r\nberapa hayo\u200b",
    "attachments": [],
    "answers": [
        {
            "answer": "<p><strong>Jawaban:</strong></p><p>1000 + 100 \u00f7 900 - 1000 \u00f7 200 =  995.111111</p><p><strong>Penjelasan dengan langkah-langkah:</strong></p><p>maaf kalau salah dan semoga membantu</p>",
            "attachments": []
        }
    ],
    "related_questions": [
        {
            "slug": "soal-trigonometri-1-sin-45-sin-60-cos-45-cos-30-356",
            "question": "Soal trigonometri    1.) Sin 45\u2070 sin 60\u2070 + cos 45\u2070 cos 30\u2070/ tan 30\u2070 tan 60\u2070\r\n\r\n2.) sin\u00b2 60\u2070 sin\u00b2 45\u2070 + cos\u00b2 30\u2070 cos\u00b2 45\u2070/ tan 30\u2070 + tan 60\u2070\r\n\r\ntolong bantu jawab soal tersebut \r\n\r\n/ = per \u200b",
            "attachments": [],
            "answers": [
                {
                    "answer": "<p><strong><em>Jawaban</em></strong><strong><em> </em></strong><strong><em>pada gambar</em></strong><strong><em> </em></strong></p><p></p><p><strong><em>Semoga membantu</em></strong><strong><em>.</em></strong><strong><em> </em></strong></p><p></p><p><strong><em>:</em></strong><strong><em>)</em></strong><strong><em> </em></strong></p>",
                    "attachments": [
                        "answer-attachments/soal-trigonometri-1-sin-45-sin-60-cos-45-cos-30-356-1.jpg",
                        "answer-attachments/soal-trigonometri-1-sin-45-sin-60-cos-45-cos-30-356-2.jpg"
                    ]
                }
            ]
        },
        {
            "slug": "14-ibu-membeli-5-ons-tomat-dan-1-kg-cabai-berat-seluruh-belanja-492",
            "question": "14. Ibu membeli 5 ons tomat dan 1 kg cabai. Berat seluruh belanjaan ibu adalah     a. 6 kg\r\nb. 15 kg\r\nc. 15 ons\u200b",
            "attachments": [],
            "answers": [
                {
                    "answer": "<p><strong>Jawaban:</strong></p><p>C. 15 ons </p><p>maaf kalau salah</p>",
                    "attachments": []
                },
                {
                    "answer": "<p>Jawab:</p><p>15 ons</p><p>Penjelasan dengan langkah-langkah:</p><p>1 kg = 10 ons</p><p>tomat = 5 ons</p><p>cabai = 1 kg = 10 ons</p><p>total berat:</p><p>= 5 ons + 10 ons</p><p>= 15 ons</p><p>    </p>",
                    "attachments": []
                }
            ]
        },
        {
            "slug": "perhatikan-gambar-berikut-965",
            "question": "Perhatikan gambar berikut!\r\n\u200b",
            "attachments": [
                "question-attachments/perhatikan-gambar-berikut-965-1.jpg"
            ],
            "answers": [
                {
                    "answer": "<h2>a. 240 cm\u00b2</h2><p></p><h3><strong><u>Pembahasan</u></strong></h3><p>L = (jumlah sisi sejajar / 2) \u00d7 tinggi</p><p>   = (10+5 / 2) \u00d7 32</p><p>   = 7,5 \u00d7 32</p><p>   = <strong>240 cm\u00b2</strong></p>",
                    "attachments": []
                }
            ]
        },
        {
            "slug": "diketahui-segitiga-siku-siku-abc-siku-siku-di-b-jika-panjang-ab-390",
            "question": "diketahui segitiga siku-siku ABC siku-siku di B jika panjang AB = 9 cm AC = 12 cm Tentukan Sin C cos C Tan C\u200b",
            "attachments": [],
            "answers": [
                {
                    "answer": "<p><strong><em>Jawaban</em></strong><strong><em> </em></strong><strong><em>pada gambar</em></strong><strong><em> </em></strong></p><p></p><p><strong><em>Semoga membantu</em></strong><strong><em>.</em></strong><strong><em> </em></strong></p><p></p><p><strong><em>:</em></strong><strong><em>)</em></strong><strong><em> </em></strong></p>",
                    "attachments": [
                        "answer-attachments/diketahui-segitiga-siku-siku-abc-siku-siku-di-b-jika-panjang-ab-390-1.jpg"
                    ]
                },
                {
                    "answer": "<p><strong>Jawaban:</strong></p><p> saya itu ganteng kayak orang koreaa</p>",
                    "attachments": []
                }
            ]
        },
        {
            "slug": "diketahui-fungsi-fx2x5x-e-r-tentukan-bayangan-untuk-x-3-247",
            "question": "Diketahui fungsi f(x)=2x\u00b2+5,x e R tentukan bayangan untuk x=-3\u200b",
            "attachments": [],
            "answers": [
                {
                    "answer": "<p><strong>Jawaban:</strong></p><p>10</p><p><strong>Penjelasan dengan langkah-langkah:</strong></p><p>maaf kalau Benar</p>",
                    "attachments": []
                }
            ]
        },
        {
            "slug": "diketahui-3loh-5y-maka-nilai-dari-15log-25-adalah-mohon-151",
            "question": "Diketahui \u00b3loh 5=y, maka nilai dari \u00b9\u2075log 25 adalah....\r\n\r\n\r\nmohon bantuannya\u200b",
            "attachments": [],
            "answers": [
                {
                    "answer": "<p>logaritma</p><p></p><p>\u00b3log 5 = y</p><p></p><p>\u00b9\u2075log 25</p><p>= \u00b3log 25 / \u00b3log 15</p><p>= \u00b3log 5\u00b2 / \u00b3log (3 \u00d7 5)</p><p>= (2 . \u00b3log 5) / (\u00b3log 3 + \u00b3log 5)</p><p>= 2y/(1 + y)</p>",
                    "attachments": []
                }
            ]
        },
        {
            "slug": "diketahui-fungsi-linier-fx-2x24x-2-nilai-dari-f4-dan-f6-136",
            "question": "Diketahui fungsi linier\r\nf(x) =2x\u00b2+4x-2\r\nNilai dari f(4) dan f(6) adalah\u200b",
            "attachments": [],
            "answers": [
                {
                    "answer": "<p><strong>Jawaban:</strong></p><p>f(4) = 46</p><p>f(6) = 94</p><p><strong>Penjelasan dengan langkah-langkah:</strong></p><p>f(x) = 2x\u00b2 + 4x - 2</p><p></p><p>f(4) = 2.4\u00b2 + 4.4 - 2</p><p>f(4) = 2.16 + 16 - 2</p><p>f(4) = 32 + 16 - 2</p><p>f(4) = 46</p><p></p><p>f(6) = 2.6\u00b2 + 4.6 - 2</p><p>f(6) =2.36 + 24 - 2</p><p>f(6) = 72 + 24 - 2</p><p>f(6) = 94</p>",
                    "attachments": []
                },
                {
                    "answer": "<h2><strong>Jawab:</strong></h2><p>f(4) = 44</p><p>f(6) = 94</p><h2>_______________________________</h2><h2><strong>Penjelasan:</strong></h2><p>f(x) = 2x\u00b2 + 4x - 2</p><p>f(4) = 2(4)\u00b2 + 4(4) - 2</p><p>f(4) = 2(16) + 16 - 2</p><p>f(4) = 32 + 16 - 2</p><p>f(4) = 48 - 2</p><p>f(4) = <strong>46</strong></p><p><strong></strong></p><p><strong></strong></p><p>f(x) = 2x\u00b2 + 4x - 2</p><p>f(6) = 2(6)\u00b2 + 4(6) - 2</p><p>f(6) = 2(36) + 24 - 2</p><p>f(6) = 72 + 24 - 2</p><p>f(6) = 96 - 2</p><p>f(6) = <strong>94</strong></p><p><strong></strong></p><p><strong></strong></p><p>mei2405~~</p>",
                    "attachments": []
                }
            ]
        },
        {
            "slug": "tolong-jawab-soal-ini-susah-710",
            "question": "Tolong jawab soal ini susah",
            "attachments": [
                "question-attachments/tolong-jawab-soal-ini-susah-710-1.png"
            ],
            "answers": [
                {
                    "answer": "<p><strong>Gatip</strong></p><p> </p><p>Gatip dalah rangkaian grafis menggunakan motif khusus yang ditemukan dalam ulos diciptakan pada saat benang diuntai dengan ukuran standard.</p><p></p><p>semoga bermanfaat terimakasih</p>",
                    "attachments": []
                },
                {
                    "answer": "<p><strong>Jawaban:</strong></p><p>IYA SUSAH KYA AKU MUVEON DARI DIA:)</p><p></p>",
                    "attachments": []
                }
            ]
        },
        {
            "slug": "menurut-fungsi-tujuan-peebuatnya-karyaseni-rupa-tiga-dimensi-dib-689",
            "question": "menurut fungsi tujuan peebuatnya, karyaseni rupa tiga dimensi dibagi menjadi seni rupa ..... dan seni rupa....\u200b",
            "attachments": [],
            "answers": [
                {
                    "answer": "<p><strong>Jawaban:</strong></p><p>gak tau hdggfhvnfcgxjg Sngsnsgdjgd</p>",
                    "attachments": []
                },
                {
                    "answer": "<p><strong>Jawaban:</strong></p><p>Seni rupa murni dan seni rupa terapan</p><p></p><p></p><p>Semoga membantu </p><p></p>",
                    "attachments": []
                }
            ]
        },
        {
            "slug": "wirawan-memenangkan-undian-hadiah-uang-tunai-dari-sebuah-bank-seb-661",
            "question": "Wirawan memenangkan undian hadiah uang tunai dari sebuah bank sebesar rp 4.000.000,00 kemudian pihak bank memberikan informasi bahwa pajak sebesar 12% ditanggung oleh pemenang. hadiah uang tunai yang diterima wirawan adalah",
            "attachments": [],
            "answers": [
                {
                    "answer": "<p><strong>Jawaban:</strong></p><p></p><p>Uang yang bersih diterima oleh wirawan adalah </p><p><strong><em>Rp. 3.520.000 </em></strong></p><p></p><p><strong><em>Note :</em></strong></p><p><strong><em>Note :jalan ada di foto </em></strong></p><p></p><p></p><p></p><p><strong><em><u>SEMOGA BERMANFAAT</u></em></strong></p><p></p><p></p>",
                    "attachments": [
                        "answer-attachments/wirawan-memenangkan-undian-hadiah-uang-tunai-dari-sebuah-bank-seb-661-1.jpg"
                    ]
                }
            ]
        }
    ]
}