{
    "question": "13. Pada waktu pergi takziah kaum ibu membawa    a. Beras\r\nb.nasi\r\nc.sambal\r\nd.kue\r\n\r\n\r\n\r\n\r\ntolong dibantu \u200b",
    "attachments": [],
    "answers": [
        {
            "answer": "<p><strong>Jawaban:</strong></p><p>a). Beras</p><p><strong>Penjelasan:</strong></p><p>maaf kalo salah</p>",
            "attachments": []
        }
    ],
    "related_questions": [
        {
            "slug": "tembang-gambuh-nduweni-guru-lagu-yoiku-341",
            "question": "Tembang Gambuh nduweni guru lagu yoiku\u200b",
            "attachments": [],
            "answers": [
                {
                    "answer": "<p><strong>Jawaban:</strong></p><p>Guru lagu yaiku tibaning swara ing saben pungkasaning gatra ( jatuhnya suara vokal di setiap akhir baris). </p><p>Guru lagune tembang gambuh = u, u, i, u, o. </p><p></p>",
                    "attachments": []
                }
            ]
        },
        {
            "slug": "langkah-pertama-dalam-membuat-gambar-cerita-adalah-plisssss-bantu-174",
            "question": "Langkah pertama dalam membuat gambar cerita adalah\r\nplisssss bantu\u200b",
            "attachments": [],
            "answers": [
                {
                    "answer": "<p><strong>Jawaban:</strong></p><p>-Tema</p><p>-Alur</p><p>-Tokoh</p><p>-Latar</p>",
                    "attachments": []
                },
                {
                    "answer": "<p><strong>Jawaban:</strong></p><p>menentukan Tema dan Judul Cergam (Gambar Cerita)</p><p><strong>Penjel</strong><strong>asan</strong><strong>:</strong></p><p><strong>Maa</strong><strong>f</strong><strong> kalo</strong><strong> salah</strong><strong>:</strong><strong>(</strong></p><p></p><p></p><p></p><p></p><p><strong>Tolo</strong><strong>ng</strong><strong> Jadikan</strong><strong> yang</strong><strong> terbaik</strong><strong> yh</strong><strong>:</strong><strong>D</strong></p><p><strong>Ser</strong><strong>ta</strong><strong> Follow</strong><strong> nanti</strong><strong> aku</strong><strong> follow</strong><strong> back</strong><strong>:</strong><strong>v</strong></p>",
                    "attachments": []
                }
            ]
        },
        {
            "slug": "47-bagaimana-cara-kerja-termos-untuk-dapat-menyimpan-panas-lebih-518",
            "question": "47. Bagaimana cara kerja termos untuk dapat menyimpan panas lebih lama?\u200b",
            "attachments": [],
            "answers": [
                {
                    "answer": "<p><strong>Jawaban:</strong></p><p>Bahan yang dipakai termos adalah isolator</p><p><strong>Penjelasan:</strong></p><p>isolator adalah benda yang tidak menghantarkan/menyerap panas, jadi ga cepat dingin.</p>",
                    "attachments": []
                },
                {
                    "answer": "<p><strong>Jawaban:</strong></p><p><strong>Dengan dinding dalam termos yang dirancang seperti kaca, maka kalor yang terdapat pada air panas tersebut tidak bisa berpindah dengan cepat. Dengan demikian, air panas tersebut dapat bertahan dalam termos ini dalam beberapa hari.</strong></p><p></p>",
                    "attachments": []
                }
            ]
        },
        {
            "slug": "bahasa-kramane-diceluk-323",
            "question": "Bahasa kramane diceluk\u200b",
            "attachments": [],
            "answers": [
                {
                    "answer": "<p><strong>Jawaban:</strong></p><p>ditimbali</p><p><strong>Penjelasan:</strong></p><p>mosok gak weruh seh</p>",
                    "attachments": []
                }
            ]
        },
        {
            "slug": "pembangunan-perahu-tradisional-diawali-dengan-pemasakan-lunas-je-581",
            "question": "Pembangunan Perahu tradisional diawali dengan pemasakan lunas. jelaskan! \u200b",
            "attachments": [],
            "answers": [
                {
                    "answer": "<p><strong>Jawaban:</strong></p><p>!Tahap pertama Tahap pertama yang dilakukan dengan menentukan hari baik untuk mencari kayu. Biasanya hari baik untuk mencari kayu jatuh pada hari ke-5 dan ke-7 di bulan yang sedang berjalan. Angka 5 menyimbolkan naparilimai dalle&#039;na yang berarti rezeki sudah ditangan. Sementara angka 7 menyimbolkan natujuangngi dalle&#039;na yang berarti selalu mendapat rezeki. Ada empat jenis kayu yang biasanya dipakai untuk membuat perahu, yakni kayu besi, kayu bikti, kayu kandole atau punaga, dan kayu jati. Tahap kedua Pada tahap kedua ada beberapa langkah, dan keunikan saat pengerjaannya. \u00a0 \u00a0 \u00a0 \u00a0 \u00a0 \u00a0 \u00a0 \u00a0 \u00a0 \u00a0 \u00a0 \u00a0 \u00a0 \u00a0 \u00a0 \u00a0 \u00a0 \u00a0 \u00a0 \u00a0 \u00a0 \u00a0 \u00a0 \u00a0 \u00a0 \u00a0 \u00a0 \u00a0 \u00a0 \u00a0 \u00a0 \u00a0 \u00a0 \u00a0 \u00a0 \u00a0 \u00a0 \u00a0 \u00a0 \u00a0 \u00a0 \u00a0 \u00a0 \u00a0 \u00a0 \u00a0 \u00a0 \u00a0 \u00a0 \u00a0 \u00a0 !Tahap kedua merupakan proses menebang, mengeringkan dan memotong kayu. Selanjutnya kayu atau bahan baku dirakit menjadi sebuah perahu dengan memasang lunas, papan, mendempul, dan memasang tiang layar. Penggabungan kayu-kayu pembuat kapal, tidak digunakan perekat seperti lem khusus kayu maupun paku. Tapi menggunakan pasak kayu, sehingga membuat bagian-bagian bisa menyatu. Pada saat peletakan lunas, harus disertai dengan proses khusus. Saat dilakukan pemotongan, lunas diletakkan menghadap timur laut. Balok lunas bagian depan merupakan simbol lelaki, sedangkan lunas bagian belakang diartikan sebagai simbol wanita. Setelah selesai diberi mantra, bagian yang dipotong ditandai dengan pahat. Pemotongan dilakukan menggunakan gergaji dan harus dilakukan tanpa boleh berhenti. Itu kenapa untuk pemotongan harus dikerjakan oleh orang-orang yang bertenaga. Demikian selanjutnya setiap tahapan selalu melalui ritual tertentu. Baca juga: Mengagumi Kapal Phinisi dari Tanjung Bira yang Mendunia \u00a0 \u00a0 \u00a0 \u00a0 \u00a0 \u00a0 \u00a0 \u00a0 \u00a0 \u00a0 \u00a0 \u00a0 \u00a0 \u00a0 \u00a0 \u00a0 \u00a0 \u00a0 \u00a0 \u00a0 \u00a0 \u00a0 \u00a0 \u00a0 \u00a0 \u00a0 \u00a0 \u00a0 \u00a0 \u00a0 \u00a0 \u00a0 \u00a0 \u00a0 \u00a0 !Tahap ketiga Proses pada tahap pertama dan kedua harus melalui beberapa langkah yang panjang dan membutuhkan waktu hingga berbulan-bulan. Untuk tahap ketiga merupakan langkah terakhir dari pembuatan Perahu Phinisi. Pada tahap terakhir ini peluncuran perahu ke laut. Sebelum perahu diluncurkan ke laut ada upacara-upacara adat yang harus dilakukan. Pada tahap ini Upacara adat yang dilaksanakan maccera lopi (mensucikan perahu) yang ditandai dengan penyembelihan binatang. Jika Perahu Phinisi berbobot kurang dari 100 ton, maka binatang yang disembelih adalah seekor kambing. Tapi, jika perahu bobotnya mencapai lebih dari 100 ton, binatang yang disembelih adalah seekor sapi.\n</p><p>\n</p><p></p><p><strong>Penjelasan:</strong></p><p></p>",
                    "attachments": []
                },
                {
                    "answer": "<p>Jawaban: asal usul kapal pinisi</p><p></p><p></p><p>Perahu Pinisi ini merupakan kapal layar kebangaan suku Bugis di Sulawesi</p><p></p><p>Ukurannya besar dan merupakan kapal legendaris Indonesia yang sudah ada sejak ribuan tahun lalu.</p><p></p><p>Perahu Pinisi adalah kapal layar khas buatan suku Bugis dan suku Makassar yang pembuatannya diwariskan secara turun temurun sejak ribuan tahun lalu.</p><p></p><p>Suku Bugis dan suku Makassar dikenal sebagai pelaut asli Indonesia.</p><p></p><p></p><p></p><p></p><p></p><p></p><p></p><p><strong>semoga</strong><strong> </strong><strong>bermanfaat</strong><strong>\uff61\u25d5\u203f\u25d5\uff61</strong></p><p></p>",
                    "attachments": []
                }
            ]
        },
        {
            "slug": "b-wangsulana-pitakon-ing-ngisor-iki-kanthi-pratitis-1-tulisen-886",
            "question": "B. Wangsulana pitakon ing ngisor iki kanthi pratitis!(    1. Tulisen nganggo aksara Jawa!\r\nKyai Dahlan nembe sesorah.\r\nWangsulan : .....\u200b",
            "attachments": [],
            "answers": [
                {
                    "answer": "<p><strong>Jawaban:</strong></p><p>aku orang kristen maaf ya gk bisa jawab ya makasih udh mau juga</p>",
                    "attachments": []
                }
            ]
        },
        {
            "slug": "untuk-memenuhi-kebutuhan-barang-yang-belum-tersedia-di-dalam-nege-622",
            "question": "untuk memenuhi kebutuhan barang yang belum tersedia di dalam negeri maka pemerintah mengadakan kegiatan ....... untuk mendatangkan barang yang dibutuhkan \u200b",
            "attachments": [],
            "answers": [
                {
                    "answer": "<p><strong>Jawaban:</strong></p><p>impor</p><p><strong>Penjelasan:</strong></p><p>impor merupakan kegiatan mendatang barang dari luar negeri sedangkan ekspor merupakan kegiatan mengirim/menjual barang ke luar negeri</p>",
                    "attachments": []
                }
            ]
        },
        {
            "slug": "8-10-tahanan-sa-padi-sebanyak-sa-nous-las-dunder-cata-sebanyak-11-157",
            "question": "8    10\r\ntahanan sa\r\nPadi sebanyak sa\r\nnous\r\nLas Dunder\r\nCata sebanyak 110\r\nata tersebut dalam bentuk\r\nagra ingkaran besar presentassen\r\nasil panen cabar adalah\u200b",
            "attachments": [],
            "answers": [
                {
                    "answer": "<p><strong>Jawaban:</strong></p><p>gue </p><p><strong>Penjelasan:</strong></p><p>gak ngerti jawabanya apa</p>",
                    "attachments": []
                }
            ]
        },
        {
            "slug": "tolong-bantu-jawab-pliss-862",
            "question": "Tolong bantu jawab pliss\u200b",
            "attachments": [
                "question-attachments/tolong-bantu-jawab-pliss-862-1.jpg"
            ],
            "answers": [
                {
                    "answer": "<p><strong>Jawaban:</strong></p><p>c.</p><p>c...................</p>",
                    "attachments": []
                },
                {
                    "answer": "<p><strong>Jawaban:</strong></p><p>1. c</p><p>2. a</p><p>maaf kalo salah^_^</p><p></p>",
                    "attachments": []
                }
            ]
        },
        {
            "slug": "jelaskan-2-manfaat-energi-panas-bagi-manusia-393",
            "question": "Jelaskan 2 manfaat energi panas bagi manusia?\u200b",
            "attachments": [],
            "answers": [
                {
                    "answer": "<p><strong>Jawaban:</strong></p><p><strong>1</strong><strong>.</strong><strong> </strong><strong>s</strong><strong>e</strong><strong>b</strong><strong>a</strong><strong>g</strong><strong>a</strong><strong>i</strong><strong> </strong><strong>p</strong><strong>e</strong><strong>m</strong><strong>b</strong><strong>a</strong><strong>n</strong><strong>g</strong><strong>k</strong><strong>i</strong><strong>t</strong><strong> </strong><strong>l</strong><strong>i</strong><strong>s</strong><strong>t</strong><strong>r</strong><strong>i</strong><strong>k</strong><strong> </strong><strong>t</strong><strong>e</strong><strong>n</strong><strong>a</strong><strong>g</strong><strong>a</strong><strong> </strong><strong>s</strong><strong>u</strong><strong>r</strong><strong>y</strong><strong>a</strong></p><p><strong>2</strong><strong>.</strong><strong> </strong><strong>m</strong><strong>e</strong><strong>n</strong><strong>j</strong><strong>e</strong><strong>m</strong><strong>u</strong><strong>r</strong><strong> </strong><strong>p</strong><strong>a</strong><strong>k</strong><strong>a</strong><strong>i</strong><strong>a</strong><strong>n</strong><strong>,</strong><strong> </strong><strong>k</strong><strong>e</strong><strong>r</strong><strong>u</strong><strong>p</strong><strong>u</strong><strong>k</strong><strong>,</strong><strong> </strong><strong>d</strong><strong>a</strong><strong>n</strong><strong> </strong><strong>i</strong><strong>k</strong><strong>a</strong><strong>n</strong></p><p></p><p><strong>s</strong><strong>e</strong><strong>m</strong><strong>o</strong><strong>g</strong><strong>a</strong><strong> </strong><strong>m</strong><strong>e</strong><strong>m</strong><strong>b</strong><strong>a</strong><strong>n</strong><strong>t</strong><strong>u</strong></p><p><strong>j</strong><strong>a</strong><strong>n</strong><strong>g</strong><strong>a</strong><strong>n</strong><strong> </strong><strong>l</strong><strong>u</strong><strong>p</strong><strong>a</strong><strong> </strong><strong>#</strong><strong>j</strong><strong>a</strong><strong>d</strong><strong>i</strong><strong>k</strong><strong>a</strong><strong>n</strong><strong>j</strong><strong>a</strong><strong>w</strong><strong>a</strong><strong>b</strong><strong>a</strong><strong>n</strong><strong>t</strong><strong>e</strong><strong>r</strong><strong>c</strong><strong>e</strong><strong>r</strong><strong>d</strong><strong>a</strong><strong>s</strong></p><p></p>",
                    "attachments": []
                }
            ]
        }
    ]
}