{
    "question": "1.Sebuah kapal belayar kearah timur sejauh 150 km,kemudian kearah selatan sejauh 200 km. hitung jarak kapal sekarang dari tempat semula.    2. Sebuah tangga yang panjangx 12 m bersandar pada tembok yg tingginya 8m. jika kaki tangga terletak 6m dari tembok maka hitunglah panjang bagian tangga yang tersisa diatas tembok\r\n\r\nMohon Bantunnya yh :)",
    "attachments": [],
    "answers": [
        {
            "answer": "1. 150+200=350<br>2. 12m-6m=12m",
            "attachments": []
        },
        {
            "answer": "1. 50\u221a34 Km <br>2. 2m<br><br>dengan rumus abc<br>",
            "attachments": []
        }
    ],
    "related_questions": [
        {
            "slug": "1-x-12-2x-36-2x45-3-24y-1133-20y-363",
            "question": "1. X-12= 2x +36\r\n2+x/4=5\r\n3. 24y-11=33-20y",
            "attachments": [],
            "answers": [
                {
                    "answer": "[tex]x-12=2x+36\\\\\n-x=48\\\\\nx=-48\\\\\\\\\n\\frac{x}{4}=5\\\\\nx=20\\\\\\\\\n24y-11=33-20y\\\\\n44y=44\\\\\ny=1[/tex]",
                    "attachments": []
                }
            ]
        },
        {
            "slug": "12-4q-5-q-5-14-q-pake-cara-775",
            "question": "1/2 (4q - 5) = q + 5 1/4\r\nq=\r\npake cara",
            "attachments": [],
            "answers": [
                {
                    "answer": "[tex]\\frac{1}{2} (4q-5) = q + 5 \\frac{1}{4} \\\\ kalikan \\ kedua \\ ruas \\ dengan \\ 4 \\\\ 4 (\\frac{1}{2})(4q-5)=4(q+5+\\frac{1}{4})\\\\ 2((4q-5)=4q+20+1\\\\ 8q-10=4q+21\\\\ 4q=31\\\\ q=\\frac{31}{4}[/tex]",
                    "attachments": []
                }
            ]
        },
        {
            "slug": "bantuin-aku-donk-5-x-54-x-58-pake-cara-ket-a-pangkatn-933",
            "question": "Bantuin aku donk..\r\n5 x (-5)'4 x 5'8 pake cara!!\r\n\r\nKet:\r\n'a= Pangkatnya ookey ;;))",
            "attachments": [],
            "answers": [
                {
                    "answer": "5 x (-5)^4 x 5^8<br><br>ingat! setiap pangkat genap, bilangan ganjil yg dipangkat menghasilan bilangan positif<br>jadi (-5)^4 sama saja dengan\u00a0(5)^4 <br><br>5 x (5)^4 x 5^8<br>=5^1 x (5)^4 x 5^8<br>=5^(1+4+8)<br>=5^13<br><br>^= pangkat <br><br><br><br><br><br><br><br>",
                    "attachments": []
                }
            ]
        },
        {
            "slug": "gan-jika-6a-2-4-jawabanya-brp-si-gankasih-tau-caranya-juga-987",
            "question": "Gan jika 6/a +2 =4 jawabanya brp si gan?kasih tau caranya juga",
            "attachments": [],
            "answers": [
                {
                    "answer": "6/a + 2 = 4<br>6/a = 2<br>6 = 2a<br>a = 6/3<br>a = 2",
                    "attachments": []
                },
                {
                    "answer": "semoga membantu dan bermanffat\u00a0<br>:)",
                    "attachments": [
                        "answer-attachments/gan-jika-6a-2-4-jawabanya-brp-si-gankasih-tau-caranya-juga-987-1.jpg"
                    ]
                }
            ]
        },
        {
            "slug": "perbandingan-kelereng-maya-dan-aldo-47-jika-selihih-kelereng-mer-892",
            "question": "perbandingan kelereng maya dan aldo 4:7 jika selihih kelereng mereka ber dua 21 , maka jumlah kerereng mereka adalah\u00a0",
            "attachments": [],
            "answers": [
                {
                    "answer": "<u></u>7-4= 3<br>maya = 4/3 \u00d7 21= 4 \u00d7 7 = 28<br>aldo = 7/3 \u00d7 21= 7 \u00d7 7 = 49<br>jumlah semua klereng = 28 + 49 = 77<br><u></u>",
                    "attachments": []
                },
                {
                    "answer": "4:7\u00a0<br>selisih adalah 21, selisih perbandingan terkecil adalah 7-4 =3<br>lalu 21/3 = 7<br>umur maya\u00a07x 4= 28<br>umur aldo\u00a07x 7 = 49<br>jadi jumlahnya\u00a028 + 49= 77",
                    "attachments": []
                }
            ]
        },
        {
            "slug": "diketahui-harga-sepasang-sepatu-dua-kali-harga-sandal-seorang-pe-782",
            "question": "diketahui harga sepasang sepatu dua kali harga sandal. seorang pedagang membeli 4 pasang sepatu dan 3 pasang sandal.pedagang tersebut harus membayar Rp.275.000,00. A.buat model matematika? B.tentukan harga 3 pasang sepatu dan 5 pasang sandal! tolong di bantu....",
            "attachments": [],
            "answers": [
                {
                    "answer": "A. Harga sepatu = x<br>\u00a0\u00a0 \u00a0  harga sandal = y<br>x=2y<br>4x+3y=275000<br>B. 3x+5y= 3.2y+5y<br>\u00a0\u00a0 \u00a0 \u00a0 =11y<br>=11.53000=\u00a0 hitung sendiri<br>",
                    "attachments": []
                }
            ]
        },
        {
            "slug": "cara-mencari-tembereng-amp-apotema-pada-lingkaran-896",
            "question": "Cara Mencari Tembereng &amp; apotema pada lingkaran",
            "attachments": [],
            "answers": [
                {
                    "answer": "Cara mencari Tembereng :<br>Luas tembereng = Luas Juring \u2013 Luas Segitiga\u00a0<br><br>",
                    "attachments": []
                },
                {
                    "answer": "kalo apotema bisa pake konsep luas segitiga sama pythagoras<br>",
                    "attachments": []
                }
            ]
        },
        {
            "slug": "cara-nyari-rumus-fungsi-dari-grafik-gimana-341",
            "question": "Cara nyari rumus fungsi dari grafik gimana?",
            "attachments": [],
            "answers": [
                {
                    "answer": "grafik yang sudah diketahui miniman 2\u00a0titik<br>[tex] \\frac{y-y1}{y2-y1} = \\frac{x-x1}{x2-x1} [/tex]<br><br>kalau grafiknya sudah diketahui gradien dan salah satu titiknya<br>y\u00a0-\u00a0y1 = m(x\u00a0-\u00a0x1)",
                    "attachments": []
                }
            ]
        },
        {
            "slug": "seorang-pedagang-membeli-2-jenis-kopi-masing-masing-sebanyak-18kg-740",
            "question": "Seorang pedagang membeli 2 jenis kopi masing-masing sebanyak 18kg dengan harga Rp 3.500 per kg dan 12 kg dengan harga Rp 3.000 per kg. kedua jenis kopi kemudian dicampur menjadi satu dan dijual dengan harga Rp 3.200 per kg. pedagang kopi tersebut akan mengalami ...    a. Rugi Rp 3.000 per kg \r\nb. Rugi Rp 3.000 \r\nc. Untung Rp 200 per kg\r\nd. Untung Rp 5.000 \r\n\r\ntolong bantu saya ya! dengan caranya Terima Kasih :)",
            "attachments": [],
            "answers": [
                {
                    "answer": "kopi 1 = 18 x 3.500 = 63.000<br>kopi 2 = 12 x 3.000 = 36.000<br>maka total nya 99.000 <br><br>kopi 1 di campur kopi 2 = 30kg x 3.200 = 96.000<br><br>maka 96.000 - 99.000 = - 3000<br>maka rugi 3.000<br>",
                    "attachments": []
                }
            ]
        },
        {
            "slug": "perbandingan-umur-dono-dan-dini-adalah-45-jika-umur-dono-40-tah-437",
            "question": "Perbandingan umur Dono dan Dini adalah 4:5. Jika Umur Dono 40 tahun. Berapakah umur Dini?",
            "attachments": [],
            "answers": [
                {
                    "answer": "perbandingan dono=4<br>dini = 5<br>dono = 40 thn<br>dini= 4\u00d740/5<br>dini 32 (perbandingan senilai)",
                    "attachments": []
                },
                {
                    "answer": "50 tahun<br>Do : Di = 4 : 5<br>4 : 5 = 40 / x<br>4x = 40.5<br>4x = 200<br>x = 200/4<br>x= 50",
                    "attachments": []
                }
            ]
        }
    ]
}