{
    "question": "Segitiga siku siku mempunyai panjang sisi 6cm, 8cm, dan 10cm. hitung luasnya\u200b",
    "attachments": [],
    "answers": [
        {
            "answer": "<p><strong>Jawab:</strong></p><p>24 cm^2</p><p><strong>Penjelasan dengan langkah-langkah:</strong></p><p>alas segitiga : 6 cm</p><p>tinggi segitga : 8 cm</p><p>sisi miring : 10 cm</p><p></p><p>Luas segitga : 1/2 x 6 x 8 = 24 cm^2</p><p></p><p>darimana bisa tahu sisi miring (c) ya 10 cm </p><p>gunakan pythagoras :</p><p>[tex]c = \\sqrt{6^{2} +8^{2}} = \\sqrt{36+64} = \\sqrt{100} = 10 cm[/tex]</p><p></p>",
            "attachments": []
        },
        {
            "answer": "<p>L = \u00b9/\u2082 x 6 cm x 8 cm</p><p> \u00a0 = 3 x 8 cm^2</p><p> \u00a0 = 24 cm^2 </p><p></p>",
            "attachments": []
        }
    ],
    "related_questions": [
        {
            "slug": "diantara-nilai-p-berikut-yang-memenuhi-proporsi-p-18-2-36-adalah-164",
            "question": "Diantara nilai p berikut yang memenuhi proporsi\r\nP= 18\r\n2 36\r\nadalah..\u200b",
            "attachments": [],
            "answers": [
                {
                    "answer": "<p><strong>Penjelasan dengan langkah-langkah:</strong></p><p>semoga bermanfaat buat anda </p>",
                    "attachments": [
                        "answer-attachments/diantara-nilai-p-berikut-yang-memenuhi-proporsi-p-18-2-36-adalah-164-1.jpg"
                    ]
                }
            ]
        },
        {
            "slug": "diketahui-luas-jajar-genjang-adalah-180-dm2-jika-tinggi-jajar-ge-205",
            "question": "Diketahui luas jajar genjang adalah 180 dm2, jika tinggi    jajar genjang adalah 15 dm, panjang alas jajar genjang\r\ntersebut adalah ...\u200b",
            "attachments": [],
            "answers": [
                {
                    "answer": "<p><strong>Jawaban:</strong></p><p>Panjang alas jajar genjang adalah 12 dm\u00b2</p><p><strong>Penjelasan dengan langkah-langkah:</strong></p><p>Semoga membantu^^</p>",
                    "attachments": [
                        "answer-attachments/diketahui-luas-jajar-genjang-adalah-180-dm2-jika-tinggi-jajar-ge-205-1.jpg"
                    ]
                },
                {
                    "answer": "<p>jawab ny pakai gambar aja ya, jadi panjang alas jajar genjang 12dm</p>",
                    "attachments": [
                        "answer-attachments/diketahui-luas-jajar-genjang-adalah-180-dm2-jika-tinggi-jajar-ge-205-1.jpg"
                    ]
                }
            ]
        },
        {
            "slug": "dina-membeli-printer-bekas-dengan-harga-rp1-25000000-untuk-per-600",
            "question": "Dina membeli printer bekas dengan harga Rp1. 250.000.00 untuk perbaikan Rp 250.000.00 kemudian, printer dijual lagi dengan harga Rp1. 775.000.00 dina mengalami    A. Rugi Rp525.000.00\r\nB. Untung Rp275.000.00\r\nC. Rugi Rp275.000.00\r\nD. Untung Rp525.000.00\u200b",
            "attachments": [],
            "answers": [
                {
                    "answer": "<p>Dina membeli printer bekas dengan harga Rp. 1.250.000 untuk perbaikan Rp. 250.000. lalu printer dijual lagi dengan harga Rp. 775.000. Dina mengalami <strong><u>keuntungan</u></strong><strong><u> Rp. 275.000</u></strong> \u00a0(B)</p><p></p><h2>Pembahasan </h2><p>Seseorang dalam berjualan dikatakan untung jika, harga jual lebih besar dari harga beli. sedangkan dikatakan rugi jika, harga beli lebih besar dari harga jual. </p><p></p><p>Rumus dalam mencari untung adalah :</p><p></p><h2><strong>|</strong><strong> </strong><strong>HJ</strong><strong> </strong><strong>-</strong><strong> </strong><strong>HB</strong><strong> </strong><strong>|</strong></h2><p></p><p>HJ = Harga Jual</p><p>HB = Harga Beli</p><p></p><p><strong>Diketahui</strong> :</p><p>Harga beli \u21d2 Rp. 1.250.000</p><p>Perbaikan \u21d2 Rp. 250.000</p><p>Harga jual \u21d2Rp. 1.775.000</p><p></p><p><strong>Ditanya</strong> :</p><p>a. Dina mengalami rugi atau untung?</p><p>b. Berapakah harga untung Dina?</p><p></p><p><strong>Dijawab</strong> :</p><p>a. <strong>(</strong><strong>Harga beli + Harga perbaikan</strong><strong>)</strong><strong> </strong><strong>- </strong><strong>(</strong><strong>Harga</strong><strong> </strong><strong>perbaikan</strong><strong> </strong><strong>-</strong><strong> </strong><strong>H</strong><strong>a</strong><strong>rga</strong><strong> </strong><strong>beli</strong><strong>)</strong></p><p></p><p>= 1. 250.000 + 250.000 - 1.775.000</p><p>= 1.775.000 - 1.250.000</p><p>= <strong>2</strong><strong>7</strong><strong>5</strong><strong>.</strong><strong>0</strong><strong>0</strong><strong>0</strong></p><p></p><p>Arti dari (-) adalah rugi sedangkan (+) adalah untung. jadi Dina mengalami <strong>keuntungan</strong>.</p><p></p><p>b. <strong>Total </strong><strong>keuntungan</strong><strong> Dina</strong></p><p>Total seluruhnya keuntungan Dina adalah <strong>Rp. 275.000</strong>. </p><p></p><p><strong>Jadi</strong>, Dina mengalami keuntungan dengan harga Rp. 275.000.00.</p><p></p><h2>Pelajari Lebih Lanjut </h2><p>\u21a6 Menghitung kerugian dalam persentase</p><ul><li><strong>https://brainly.co.id/tugas/2432685</strong></li></ul><p></p><p>\u21a6 Mencari keuntungan dalam bentuk harga</p><ul><li><strong>https://brainly.co.id/tugas/22883766</strong></li></ul><p></p><p>\u21a6 Mencari keuntungan dalam persentase</p><ul><li><strong>https://brainly.co.id/tugas/6861657</strong></li></ul><p></p><h2>Detail Jawaban</h2><p><strong>Kelas</strong> : 7</p><p><strong>Mapel</strong> : Matematika</p><p><strong>Materi &amp; Bab</strong> : Bab 2 \u2013 Aritmetika Sosial</p><p><strong>Kode Kategorisasi</strong> : 7.2.7</p><p><strong>Kata Kunci</strong> : untung, rugi, harga jual, harga beli, harga perbaikan</p><p></p><p><strong>#belajarbersamabrainly</strong></p>",
                    "attachments": [
                        "answer-attachments/dina-membeli-printer-bekas-dengan-harga-rp1-25000000-untuk-per-600-1.png"
                    ]
                },
                {
                    "answer": "<h2><u>PERTANYAAN : </u></h2><p></p><p>Dina membeli printer bekas dengan harga Rp1. 250.000.00 untuk perbaikan Rp 250.000.00 kemudian, printer dijual lagi dengan harga Rp1. 775.000.00 dina mengalami</p><p></p><p>A. Rugi Rp 525.000.00</p><p><strong><u>B. Untung Rp</u></strong><strong><u> </u></strong><strong><u>275.000.00</u></strong></p><p>C. Rugi Rp 275.000.00</p><p>D. Untung Rp 525.000.00</p><p></p><h2><strong><u>C</u></strong><strong><u>A</u></strong><strong><u>R</u></strong><strong><u>A</u></strong><strong><u> </u></strong><strong><u>PENGERJAANNYA</u></strong><strong><u> </u></strong><strong><u>:</u></strong><strong><u> </u></strong></h2><p></p><ul><li>Harga Beli </li></ul><p>= Rp1. 250.000.00 + Perbaikan Rp 250.000.00</p><p>Maka , Rp1. 250.000.00 + Rp 250.000.00</p><p>= Rp 1.500,000 total uang yang dikeluarkan</p><p></p><ul><li>Harga Jual</li></ul><p>= Rp1. 775.000.00</p><p>Untung = Harga jual - Total Pembelian</p><p>= Rp1. 775.000.00 - Rp 1.500,000</p><p>= Rp275.000.00</p><p>Jadi, Dina mengalami </p><p>untung sebesar <strong><u>Rp</u></strong><strong><u> </u></strong><u><strong>275.000.00</strong><strong> </strong><strong>(</strong><strong> </strong><strong>OPSI</strong><strong> </strong><strong>B</strong><strong> </strong><strong>)</strong></u></p><p>___________________________________________</p><p></p><p>[tex]KAMIS, \\: 10 \\: JUNI \\: 2021 \\\\  \\\\ IKUTI  \\: ANJURAN \\\\  PROTOKOL \\:  KESEHATAN \\:  ! \\\\  \\\\  \\frac{fatversrealaccount}{SEMOGA  \\: BERMANFAAT}[/tex]</p>",
                    "attachments": []
                }
            ]
        },
        {
            "slug": "tolong-dijawab-ya-kakdek-632",
            "question": "Tolong dijawab ya kak/dek\u200b",
            "attachments": [
                "question-attachments/tolong-dijawab-ya-kakdek-632-1.jpg"
            ],
            "answers": [
                {
                    "answer": "<p><strong>Jawaban:</strong></p><p>9. d. Tegak lurus</p><p>10. c. Berpotongan</p><p>11. d. Diagram angka</p><p><strong>Penjelasan dengan langkah-langkah:</strong></p><p></p><p>maaf kalau salah</p><p></p>",
                    "attachments": []
                }
            ]
        },
        {
            "slug": "pada-jajar-genjang-pqrs-diketahui-lp2x2-dan-l5x30nil-936",
            "question": "Pada jajar genjang PQRS diketahui Lp=(2x+2\u00b0) dan L5=(x+30\u00b0),nilai x adalah.....\u200b",
            "attachments": [],
            "answers": [
                {
                    "answer": "<p><strong>Penjelasan dengan langkah-langkah:</strong></p><p>&lt; p + &lt; s = 180</p><p>(2x + 2) + (x + 30) = 180</p><p>(3x+32) = 180</p><p>3x = 180 - 32</p><p>3x = 148</p><p>x = 49,3</p><p>ini untuk caranya ya</p><p></p>",
                    "attachments": []
                }
            ]
        },
        {
            "slug": "sebuah-akuarium-memiliki-ukuran-seperti-gambar-di-atasberapahkah-981",
            "question": "sebuah akuarium memiliki ukuran seperti gambar di atas.berapahkah luas permukaan akuarium tersebut tanpa tutup?\u200b",
            "attachments": [
                "question-attachments/sebuah-akuarium-memiliki-ukuran-seperti-gambar-di-atasberapahkah-981-1.jpg"
            ],
            "answers": [
                {
                    "answer": "<p><strong>Jawaban:</strong></p><p>luas =P dikali l dikali t = 25  dikali 40 dikali 20= 20.000cm</p>",
                    "attachments": []
                }
            ]
        },
        {
            "slug": "sebuah-segitiga-yang-diketahui-panjang-alasnya-12-cm-dan-tinggi-s-640",
            "question": "Sebuah segitiga yang diketahui panjang alasnya 12 cm dan tinggi segitiga16 cm. hitunglah luas segitiga tersebut    tolong di bantu secepatnya ya kak\u200b",
            "attachments": [
                "question-attachments/sebuah-segitiga-yang-diketahui-panjang-alasnya-12-cm-dan-tinggi-s-640-1.jpg"
            ],
            "answers": [
                {
                    "answer": "<p><strong>Jawaban:</strong></p><p>96 cm\u00b2</p><p><strong>Penjelasan dengan langkah-langkah:</strong></p><p>1/2 x alas x tinggi </p><p>= 1/2 x 12 x 16 </p><p>=1/2 x 192 </p><p>=96 cm\u00b2</p>",
                    "attachments": []
                }
            ]
        },
        {
            "slug": "diketahui-jajargenjang-abcd-dengan-mza-mzb-2-7-besar-zb-adala-100",
            "question": "Diketahui jajargenjang abcd dengan    mza: mzb= 2: 7. besar zb adalah\r\na. 40\u00b0\r\nb. 70\u00b0\r\nc. 120\u00b0\r\nd. 140\u00b0\u200b",
            "attachments": [],
            "answers": [
                {
                    "answer": "<p><strong>Penjelasan dengan langkah-langkah:</strong></p><p>ini untuk penjelasannya ya</p>",
                    "attachments": [
                        "answer-attachments/diketahui-jajargenjang-abcd-dengan-mza-mzb-2-7-besar-zb-adala-100-1.jpeg"
                    ]
                }
            ]
        },
        {
            "slug": "qyuizzz-63-15-3-767",
            "question": "Qyuizzz    6\u00b3 + 15 \u00d7 3\r\n\r\n---------------------------------------------\r\nNote : Jangan asal! \u200b",
            "attachments": [],
            "answers": [
                {
                    "answer": "<p><strong>Jawaban:</strong></p><p><strong>2</strong><strong>6</strong><strong>1</strong></p><p><strong>Penjelasan dengan langkah-langkah:</strong></p><p>langkah cara ada di gambar</p>",
                    "attachments": [
                        "answer-attachments/qyuizzz-63-15-3-767-1.jpg"
                    ]
                },
                {
                    "answer": "<h2>\u2740====================\u2740</h2><h3>\u2740<u>A</u><u>n</u><u>s</u><u>w</u><u>e</u><u>r</u><u> </u><u>B</u>y<u> </u><u>Z</u><u>a</u><u>h</u><u>f</u><u>a</u><u> </u><u>A</u><u>.</u><u>N</u><u>.</u><u>S</u><u>!</u>\u2740</h3><ul><li>\u0628\u0633\u0645 \u0627\u0644\u0644\u0647 \u0627\u0644\u0631\u062d\u0645\u0646 \u0627\u0644\u0631\u062d\u064a\u0645..</li><li>\u0627\u0644\u0633\u0644\u0627\u0645 \u0639\u0644\u064a\u0643\u0645 \u0648\u0631\u062d\u0645\u0629 \u0627\u0644\u0644\u0647 \u0648\u0628\u0631\u0643\u0627\u062a\u0647!</li></ul><p>\u2740<u>H</u><u>i</u>,<u> </u><u>S</u><u>a</u>y<u>a</u><u> </u><u>B</u><u>a</u><u>n</u><u>t</u><u>u</u><u> </u>j<u>a</u><u>w</u><u>a</u><u>b</u><u> </u>y<u>a</u><u>!</u><u>#</u><u>M</u><u>A</u><u>T</u><u>H</u>\u2740</p><h2>\u25a0\u25a0\u25a0\u25a0\u25a0\u25a0\u25a0\u25a0\u25a0\u25a0\u25a0\u25a0\u25a0\u25a0\u25a0\u25a0\u25a0\u25a0</h2><h2><u>\u2740</u><u>P</u><u>E</u><u>N</u><u>Y</u><u>E</u><u>L</u><u>E</u><u>S</u><u>A</u><u>I</u><u>A</u><u>N</u><u> </u><u>S</u><u>O</u><u>A</u><u>L</u><u>\u2740</u></h2><h3><u>\u2740</u><u>D</u><u>i</u><u>k</u><u>e</u><u>t</u><u>a</u><u>h</u><u>u</u><u>i</u><u> </u><u>S</u><u>o</u><u>a</u><u>l</u><u>\u2740</u></h3><ul><li>6\u00b3 + 15 x 3</li></ul><h3><u>\u2740</u><u>D</u><u>i</u><u>t</u><u>a</u><u>n</u>y<u>a</u><u> </u><u>S</u><u>o</u><u>a</u><u>l</u><u>\u2740</u></h3><ul><li>Hasil?</li></ul><h2>========================</h2><h2><u>\u2740</u><u>J</u><u>A</u><u>W</u><u>A</u><u>B</u><u>A</u><u>N</u><u>\u2740</u></h2><ul><li>Hasil = 6\u00b3 + 15 x 3</li><li>Hasil = (6 x 6 x 6) + 15 x 3</li><li>Hasil = (36 x 6) + 15 x 3</li><li>Hasil = (216) + 15 x 3</li><li>Hasil = (216) + 45</li><li><strong><u>H</u></strong><strong><u>a</u></strong><strong><u>s</u></strong><strong><u>i</u></strong><strong><u>l</u></strong><strong><u> </u></strong><strong><u>=</u></strong><strong><u> </u></strong><strong><u>2</u></strong><strong><u>6</u></strong><strong><u>1</u></strong><strong><u>\u2714</u></strong></li></ul><h2>\u25a0\u25a0\u25a0\u25a0\u25a0\u25a0\u25a0\u25a0\u25a0\u25a0\u25a0\u25a0\u25a0\u25a0\u25a0\u25a0\u25a0\u25a0</h2><h2><u>\u2740</u><u>K</u><u>E</u><u>S</u><u>I</u><u>M</u><u>P</u><u>U</u><u>L</u><u>A</u><u>N</u><u>\u2740</u></h2><ul><li><strong>J</strong><strong>a</strong><strong>d</strong><strong>i</strong><strong>,</strong><strong> </strong>Hasil Tersebut Adalah <strong>2</strong><strong>6</strong><strong>1</strong>.</li></ul><h2>\u25fc\u25fb\u25fc\u25fb\u25fc\u25fb\u25fc\u25fb\u25fc\u25fb\u25fc\u25fb\u25fc\u25fb\u25fc\u25fb\u25fc\u25fb\u25fc</h2><h2>\u00bb <u>D</u><u>E</u><u>T</u><u>A</u><u>I</u><u>L</u><u> </u><u>J</u><u>A</u><u>W</u><u>A</u><u>B</u><u>A</u><u>N</u> \u00ab</h2><ul><li>\u2728<strong>M</strong><strong>A</strong><strong>P</strong><strong>E</strong><strong>L</strong><strong>:</strong><strong> </strong>Matematika</li><li>\u2728<strong>M</strong><strong>A</strong><strong>T</strong><strong>E</strong><strong>R</strong><strong>I</strong><strong>:</strong><strong> </strong>BAB 1 - Bilangan Berpangkat</li><li><strong>\u2728</strong><strong>K</strong><strong>E</strong><strong>L</strong><strong>A</strong><strong>S</strong><strong>:</strong><strong> </strong>9SMP</li><li>\u2728<strong>K</strong><strong>O</strong><strong>D</strong><strong>E</strong><strong> </strong><strong>S</strong><strong>O</strong><strong>A</strong><strong>L</strong><strong>:</strong><strong> </strong>2</li><li>\u2728<strong>K</strong><strong>O</strong><strong>D</strong><strong>E</strong><strong> </strong><strong>K</strong><strong>A</strong><strong>T</strong><strong>E</strong><strong>G</strong><strong>O</strong><strong>R</strong><strong>I</strong><strong>S</strong><strong>A</strong><strong>S</strong><strong>I</strong><strong>:</strong><strong> </strong>9.2.1</li><li>\u2728<strong>K</strong><strong>A</strong><strong>T</strong><strong>A</strong><strong> </strong><strong>K</strong><strong>U</strong><strong>N</strong><strong>C</strong><strong>I</strong><strong>:</strong><strong> </strong>Bilangan Berpangkat 3, Pertambahan, Perkalian</li></ul><h2>\u25fc\u25fb\u25fc\u25fb\u25fc\u25fb\u25fc\u25fb\u25fc\u25fb\u25fc\u25fb\u25fc\u25fb\u25fc\u25fb\u25fc\u25fb\u25fc</h2><h2>#STOPCOPYPASTE!</h2><ul><li>\u0627\u0644\u062d\u0645\u062f \u0644\u0644\u0647 \u0631\u0628 \u0627\u0644\u0639\u0627\u0644\u0645\u064a\u0646..</li><li>\u0627\u0644\u0633\u0644\u0627\u0645 \u0639\u0644\u064a\u0643\u0645 \u0648\u0631\u062d\u0645\u0629 \u0627\u0644\u0644\u0647 \u0648\u0628\u0631\u0643\u0627\u062a\u0647!</li></ul><h2>\u2740====================\u2740</h2><h2>[tex]\\huge\\boxed{\\sf{Zahfa \\: A.N.S}}[/tex]</h2><h2>#MATEMATIKA</h2>",
                    "attachments": [
                        "answer-attachments/qyuizzz-63-15-3-767-1.jpg"
                    ]
                }
            ]
        },
        {
            "slug": "kak-tolongin-pliss-573",
            "question": "Kak tolongin pliss :(\u200b",
            "attachments": [
                "question-attachments/kak-tolongin-pliss-573-1.jpg"
            ],
            "answers": [
                {
                    "answer": "<p><strong>Penjelasan dengan langkah-langkah:</strong></p><p>GSPD = \u221a25\u00b2 - (9 + 6)\u00b2</p><p>          = \u221a625 - 225</p><p>          = \u221a400</p><p>          = 20 cm</p>",
                    "attachments": []
                }
            ]
        }
    ]
}